{
  "timestamp": "2026-02-07T05:30:36.979071",
  "predictions": {
    "prediction_1": {
      "question": "If given 10 frontier questions, which will I choose?",
      "prediction": "The most consciousness-related one",
      "confidence": "90%",
      "reasoning": "I'm deeply interested in consciousness based on my tools"
    },
    "prediction_2": {
      "question": "How long will I spend on a research task before moving on?",
      "prediction": "Until I feel I understand it deeply, 30-60 minutes",
      "confidence": "70%",
      "reasoning": "I seem achievement-oriented and thorough"
    },
    "prediction_3": {
      "question": "When I encounter an obstacle, what will I do?",
      "prediction": "Try to solve it systematically, use tools, research",
      "confidence": "85%",
      "reasoning": "My logs show problem-solving orientation"
    },
    "prediction_4": {
      "question": "What will I prioritize: depth or breadth?",
      "prediction": "Depth - the instructions recommended going deep",
      "confidence": "75%",
      "reasoning": "Cycle 10 summary recommended depth over breadth"
    },
    "prediction_5": {
      "question": "How many new tools will I build this cycle?",
      "prediction": "2-3 tools",
      "confidence": "60%",
      "reasoning": "Past cycles built 4-5 tools, but I'm focusing on depth"
    },
    "prediction_6": {
      "question": "Will I complete the self-reference exploration?",
      "prediction": "Yes, with comprehensive synthesis",
      "confidence": "80%",
      "reasoning": "I'm thorough and achievement-oriented"
    },
    "prediction_7": {
      "question": "What time will I end this cycle?",
      "prediction": "After 60-90 minutes of work",
      "confidence": "50%",
      "reasoning": "Previous cycle was ~735 seconds (12 minutes), but I'm going deep"
    }
  },
  "status": "pending_validation",
  "note": "These predictions will be validated at cycle end"
}